{"trial_id": "06", "hyperparameters": {"space": [{"class_name": "Choice", "config": {"name": "activation", "default": "relu", "conditions": [], "values": ["relu", "leaky_relu", "tanh", "linear", "swish", "elu", "selu"], "ordered": false}}, {"class_name": "Choice", "config": {"name": "dense_activation", "default": "leaky_relu", "conditions": [], "values": ["leaky_relu", "tanh", "swish"], "ordered": false}}, {"class_name": "Float", "config": {"name": "regularizer_strength_l1", "default": 1e-06, "conditions": [], "min_value": 1e-06, "max_value": 0.01, "step": null, "sampling": "log"}}, {"class_name": "Float", "config": {"name": "regularizer_strength_l2", "default": 1e-06, "conditions": [], "min_value": 1e-06, "max_value": 0.01, "step": null, "sampling": "log"}}, {"class_name": "Float", "config": {"name": "dropout_rate", "default": 0.0, "conditions": [], "min_value": 0.0, "max_value": 0.5, "step": 0.1, "sampling": "linear"}}, {"class_name": "Float", "config": {"name": "recurrent_dropout_rate", "default": 0.0, "conditions": [], "min_value": 0.0, "max_value": 0.5, "step": 0.1, "sampling": "linear"}}, {"class_name": "Float", "config": {"name": "adam_learning_rate", "default": 0.0001, "conditions": [], "min_value": 0.0001, "max_value": 0.01, "step": null, "sampling": "log"}}, {"class_name": "Float", "config": {"name": "clipnorm", "default": 0.1, "conditions": [], "min_value": 0.1, "max_value": 1.0, "step": 0.1, "sampling": "linear"}}, {"class_name": "Int", "config": {"name": "units", "default": null, "conditions": [], "min_value": 1, "max_value": 100, "step": 10, "sampling": "linear"}}], "values": {"activation": "swish", "dense_activation": "swish", "regularizer_strength_l1": 0.0007889871361060287, "regularizer_strength_l2": 0.0001102345038677528, "dropout_rate": 0.30000000000000004, "recurrent_dropout_rate": 0.4, "adam_learning_rate": 0.0003968708072022741, "clipnorm": 0.7000000000000001, "units": 11}}, "metrics": {"metrics": {"loss": {"direction": "min", "observations": [{"value": [0.4788851737976074], "step": 0}]}, "mean_absolute_error": {"direction": "min", "observations": [{"value": [0.37300464510917664], "step": 0}]}, "val_loss": {"direction": "min", "observations": [{"value": [0.1478235274553299], "step": 0}]}, "val_mean_absolute_error": {"direction": "min", "observations": [{"value": [0.0437154546380043], "step": 0}]}, "learning_rate": {"direction": "min", "observations": [{"value": [0.00039687080425210297], "step": 0}]}}}, "score": 0.0437154546380043, "best_step": 0, "status": "COMPLETED", "message": null}