{"trial_id": "19", "hyperparameters": {"space": [{"class_name": "Choice", "config": {"name": "activation", "default": "relu", "conditions": [], "values": ["relu", "leaky_relu", "tanh", "linear"], "ordered": false}}, {"class_name": "Float", "config": {"name": "regularizer_strength_l1", "default": 1e-06, "conditions": [], "min_value": 1e-06, "max_value": 0.01, "step": null, "sampling": "log"}}, {"class_name": "Float", "config": {"name": "regularizer_strength_l2", "default": 1e-06, "conditions": [], "min_value": 1e-06, "max_value": 0.01, "step": null, "sampling": "log"}}, {"class_name": "Int", "config": {"name": "units", "default": null, "conditions": [], "min_value": 1, "max_value": 20, "step": 1, "sampling": "linear"}}, {"class_name": "Choice", "config": {"name": "dense_activation", "default": "linear", "conditions": [], "values": ["linear", "leaky_relu", "tanh"], "ordered": false}}, {"class_name": "Choice", "config": {"name": "optimizer", "default": "adam", "conditions": [], "values": ["adam", "rmsprop"], "ordered": false}}, {"class_name": "Float", "config": {"name": "adam_learning_rate", "default": 0.0001, "conditions": [], "min_value": 0.0001, "max_value": 0.001, "step": null, "sampling": "log"}}, {"class_name": "Float", "config": {"name": "rmsprop_learning_rate", "default": 0.0001, "conditions": [], "min_value": 0.0001, "max_value": 0.001, "step": null, "sampling": "log"}}], "values": {"activation": "relu", "regularizer_strength_l1": 0.0037187535099586595, "regularizer_strength_l2": 8.018049288865912e-06, "units": 17, "dense_activation": "linear", "optimizer": "rmsprop", "adam_learning_rate": 0.00020399947163553725, "rmsprop_learning_rate": 0.0004622521280888501}}, "metrics": {"metrics": {"loss": {"direction": "min", "observations": [{"value": [0.0022657490335404873], "step": 99}]}, "mean_squared_error": {"direction": "min", "observations": [{"value": [9.605952072888613e-05], "step": 99}]}, "val_loss": {"direction": "min", "observations": [{"value": [0.0022798439022153616], "step": 99}]}, "val_mean_squared_error": {"direction": "min", "observations": [{"value": [0.00010746814223239198], "step": 99}]}}}, "score": 0.0022798439022153616, "best_step": 99, "status": "COMPLETED", "message": null}